{"otherData": {},"traceEvents":[{},{"cat":"function","dur":0,"name":"virtual Vortex::Application::~Application()","ph":"X","pid":0,"tid":128816298883072,"ts":13423299395.386},{"cat":"function","dur":0,"name":"virtual void Sandbox2D::OnDetach()","ph":"X","pid":0,"tid":128816298883072,"ts":13423299420.814},{"cat":"function","dur":13,"name":"virtual Vortex::OpenGLTexture2D::~OpenGLTexture2D()","ph":"X","pid":0,"tid":128816298883072,"ts":13423299450.911},{"cat":"function","dur":1169,"name":"virtual void Vortex::ImGuiLayer::OnDetach()","ph":"X","pid":0,"tid":128816298883072,"ts":13423299498.794},{"cat":"function","dur":11869,"name":"void Vortex::LinuxWindow::Shutdown()","ph":"X","pid":0,"tid":128816298883072,"ts":13423300744.408},{"cat":"function","dur":11971,"name":"virtual Vortex::LinuxWindow::~LinuxWindow()","ph":"X","pid":0,"tid":128816298883072,"ts":13423300741.993}]}